class ClsObjDemo{

		int age=10;
		int jerNo=7;
		void fun(){

			int x=10;
		}
	}

	
 /*       class ObjClsDemo {
  int age;

  int jerNo;

  ObjClsDemo();
    Code:
       0: aload_0
       1: invokespecial #1                  // Method java/lang/Object."<init>":()V
       4: aload_0
       5: bipush        10
       7: putfield      #2                  // Field age:I
      10: aload_0
      11: bipush        7
      13: putfield      #3                  // Field jerNo:I
      16: return

  void fun();
    Code:
       0: bipush        10
       2: istore_1
       3: return
}*/

